<?xml version="1.0" encoding="utf-8"?>
<odoo>
    <data noupdate="1">
        <record id="motorcycle_01" model="motorcycle.registry">
            <field name="registry_number">MRN0001</field>
            <field name="vin">AZBY19H1000002</field>
        </record>
        <record id="motorcycle_02" model="motorcycle.registry">
            <field name="registry_number">MRN0002</field>
            <field name="vin">BYCX20I2000003</field>
        </record>
        <record id="motorcycle_03" model="motorcycle.registry">
            <field name="registry_number">MRN0003</field>
            <field name="vin">CXDW21J3000004</field>
        </record>
    </data>
</odoo>
